orange3_autogluon_timeseries-1.5.0-py3.9-nspkg.pth
orangecontrib/autogluon_timeseries/__init__.py
orangecontrib/autogluon_timeseries/widgets/__init__.py
orangecontrib/autogluon_timeseries/widgets/widget_autogluon.py
orangecontrib/autogluon_timeseries/widgets/icons/ItemTimeSeries.png
orangecontrib/autogluon_timeseries/widgets/icons/autogluon.png
orange3_autogluon_timeseries-1.5.0.dist-info/METADATA
orange3_autogluon_timeseries-1.5.0.dist-info/WHEEL
orange3_autogluon_timeseries-1.5.0.dist-info/entry_points.txt
orange3_autogluon_timeseries-1.5.0.dist-info/namespace_packages.txt
orange3_autogluon_timeseries-1.5.0.dist-info/top_level.txt
orange3_autogluon_timeseries-1.5.0.dist-info/RECORD
