Metadata-Version: 2.4
Name: orange3-autogluon-timeseries
Version: 1.5.0
Summary: AutoGluon Time Series forecasting widget for Orange3 with local Chronos support
Home-page: https://github.com/KordyakIM/autogluon-timeseries-widget
Author: Иван Кордяк
Author-email: KordyakIM@gmail.com
License: MIT
Keywords: orange3 add-on,time series,forecasting,autogluon,chronos,local models,offline
Classifier: License :: OSI Approved :: MIT License
Classifier: Programming Language :: Python :: 3.9
Classifier: Programming Language :: Python :: 3.10
Classifier: Programming Language :: Python :: 3.11
Classifier: Operating System :: OS Independent
Classifier: Development Status :: 4 - Beta
Classifier: Intended Audience :: Science/Research
Classifier: Topic :: Scientific/Engineering :: Artificial Intelligence
Classifier: Topic :: Scientific/Engineering :: Information Analysis
Requires-Python: >=3.9
Requires-Dist: Orange3>=3.39.0
Requires-Dist: autogluon.timeseries>=1.3.1
Requires-Dist: pandas<2.3,>=2.2
Requires-Dist: numpy>=1.25
Requires-Dist: PyQt5>=5.15
Requires-Dist: matplotlib>=3.5
Requires-Dist: holidays>=0.20
Requires-Dist: requests>=2.25.0
Requires-Dist: transformers>=4.30.0
Requires-Dist: huggingface-hub>=0.16.0
Requires-Dist: torch>=2.0.0
Requires-Dist: safetensors>=0.3.0
Dynamic: author
Dynamic: author-email
Dynamic: classifier
Dynamic: description
Dynamic: description-content-type
Dynamic: home-page
Dynamic: keywords
Dynamic: license
Dynamic: requires-dist
Dynamic: requires-python
Dynamic: summary
